README.txt
setup.py
genxmlif/__init__.py
genxmlif/xmlif4Dom.py
genxmlif/xmlifApi.py
genxmlif/xmlifBase.py
genxmlif/xmlifDom.py
genxmlif/xmlifElementTree.py
genxmlif/xmlifMinidom.py
genxmlif/xmlifODict.py
genxmlif/xmlifUtils.py
genxmlif/xmliftest.py
minixsv/__init__.py
minixsv/minixsvWrapper.py
minixsv/pyxsval.py
minixsv/xsvalBase.py
minixsv/xsvalErrorHandler.py
minixsv/xsvalSchema.py
minixsv/xsvalSimpleTypes.py
minixsv/xsvalUtils.py
minixsv/xsvalXmlIf.py
minixsv.egg-info/PKG-INFO
minixsv.egg-info/SOURCES.txt
minixsv.egg-info/dependency_links.txt
minixsv.egg-info/top_level.txt
