Metadata-Version: 1.0
Name: minixsv
Version: 0.9.0
Summary: A lightweight XML schema validator written in pure Python
Home-page: http://www.leuthe-net.de/MiniXsv.html
Author: Roland Leuthe
Author-email: roland@leuthe-net.de
License: Python (MIT style)
Platform: Python 2.4 and later
Classifier: Development Status :: 4 - Beta
Classifier: Operating System :: OS Independent
Classifier: Topic :: Text Processing :: Markup :: XML
